snipinator/__init__.py
snipinator/cli.py
snipinator/snipinate.py
snipinator/snipinate_test.py
snipinator/examples/code.py
snipinator/examples/code_test.py
snipinator/private/__init__.py
snipinator/private/utilities.py
snipinator-3.1.2.dist-info/LICENSE.md
snipinator-3.1.2.dist-info/METADATA
snipinator-3.1.2.dist-info/WHEEL
snipinator-3.1.2.dist-info/entry_points.txt
snipinator-3.1.2.dist-info/top_level.txt
snipinator-3.1.2.dist-info/RECORD
