Metadata-Version: 2.1
Name: snipinator
Version: 3.1.2
Summary: Python code snippets for markdown files, e.g READMEs, from actual (testable) code.
Author-email: AYF <realazthat@gmail.com>
License: MIT License
Project-URL: Homepage, https://github.com/realazthat/snipinator
Project-URL: Documentation, https://github.com/realazthat/snipinator
Project-URL: Repository, https://github.com/realazthat/snipinator
Keywords: github,testing,markdown,readme,snippets,documentation,jinja2,templates,preprocessor,documentation-tool,include,readme-template,readme-md,dynamic-documentation
Classifier: Operating System :: OS Independent
Classifier: Programming Language :: Python :: 3.8
Classifier: Programming Language :: Python :: 3.9
Classifier: Programming Language :: Python :: 3.10
Classifier: Programming Language :: Python :: 3.11
Classifier: Programming Language :: Python :: 3.12
Requires-Python: >=3.8
License-File: LICENSE.md
Requires-Dist: colorama<1,>=0.4
Requires-Dist: defusedxml<1,>=0.7
Requires-Dist: Jinja2<4,>=3
Requires-Dist: markdown-it-py<4,>=3
Requires-Dist: MarkupSafe<3,>=2
Requires-Dist: mdurl<1
Requires-Dist: pexpect<5,>4
Requires-Dist: ptyprocess<0.8,>=0.7
Requires-Dist: pyyaml<7,>=6
Requires-Dist: Pygments<3,>=2
Requires-Dist: rich<14,>=13
Requires-Dist: rich-argparse<2,>=1
Requires-Dist: types-colorama<1,>=0.4
Requires-Dist: typing-extensions<5,>=4
Requires-Dist: types-pyyaml<7,>=6
Requires-Dist: importlib-metadata; python_version < "3.8"
Provides-Extra: dev
Requires-Dist: argcomplete==3.2.3; extra == "dev"
Requires-Dist: autoflake==2.3.1; extra == "dev"
Requires-Dist: beautifulsoup4==4.12.3; extra == "dev"
Requires-Dist: bs4==0.0.2; extra == "dev"
Requires-Dist: build==1.0.3; extra == "dev"
Requires-Dist: certifi==2024.2.2; extra == "dev"
Requires-Dist: cffi==1.16.0; extra == "dev"
Requires-Dist: cfgv==3.4.0; extra == "dev"
Requires-Dist: changeguard==0.3.1; extra == "dev"
Requires-Dist: charset-normalizer==3.3.2; extra == "dev"
Requires-Dist: click==8.1.7; extra == "dev"
Requires-Dist: colorama==0.4.6; extra == "dev"
Requires-Dist: cryptography==42.0.5; extra == "dev"
Requires-Dist: defusedxml==0.7.1; extra == "dev"
Requires-Dist: distlib==0.3.8; extra == "dev"
Requires-Dist: docutils==0.20.1; extra == "dev"
Requires-Dist: filelock==3.13.1; extra == "dev"
Requires-Dist: identify==2.5.35; extra == "dev"
Requires-Dist: idna==3.6; extra == "dev"
Requires-Dist: importlib-metadata==7.0.2; extra == "dev"
Requires-Dist: importlib-resources==6.3.1; extra == "dev"
Requires-Dist: isort==5.13.2; extra == "dev"
Requires-Dist: jaraco-classes==3.3.1; extra == "dev"
Requires-Dist: jeepney==0.8.0; extra == "dev"
Requires-Dist: jinja2==3.1.3; extra == "dev"
Requires-Dist: keyring==24.3.1; extra == "dev"
Requires-Dist: markdown-it-py==3.0.0; extra == "dev"
Requires-Dist: markupsafe==2.1.5; extra == "dev"
Requires-Dist: mdformat==0.7.17; extra == "dev"
Requires-Dist: mdformat-gfm==0.3.0; extra == "dev"
Requires-Dist: mdformat-tables==0.4.1; extra == "dev"
Requires-Dist: mdit-py-plugins==0.4.0; extra == "dev"
Requires-Dist: mdreftidy==0.3.0; extra == "dev"
Requires-Dist: mdremotifier==0.3.1; extra == "dev"
Requires-Dist: mdurl==0.1.2; extra == "dev"
Requires-Dist: mistletoe==1.3.0; extra == "dev"
Requires-Dist: more-itertools==10.2.0; extra == "dev"
Requires-Dist: mypy==1.8.0; extra == "dev"
Requires-Dist: mypy-extensions==1.0.0; extra == "dev"
Requires-Dist: nh3==0.2.15; extra == "dev"
Requires-Dist: nodeenv==1.8.0; extra == "dev"
Requires-Dist: packaging==23.2; extra == "dev"
Requires-Dist: pathspec==0.12.1; extra == "dev"
Requires-Dist: pexpect==4.9.0; extra == "dev"
Requires-Dist: pip-licenses==4.3.4; extra == "dev"
Requires-Dist: pip-tools==7.3.0; extra == "dev"
Requires-Dist: pkginfo==1.9.6; extra == "dev"
Requires-Dist: platformdirs==4.2.0; extra == "dev"
Requires-Dist: pre-commit==3.5.0; extra == "dev"
Requires-Dist: prettytable==3.10.0; extra == "dev"
Requires-Dist: ptyprocess==0.7.0; extra == "dev"
Requires-Dist: pycparser==2.21; extra == "dev"
Requires-Dist: pyflakes==3.2.0; extra == "dev"
Requires-Dist: pygments==2.17.2; extra == "dev"
Requires-Dist: pyproject-hooks==1.0.0; extra == "dev"
Requires-Dist: pyright==1.1.352; extra == "dev"
Requires-Dist: pyyaml==6.0.1; extra == "dev"
Requires-Dist: readme-renderer==43.0; extra == "dev"
Requires-Dist: requests==2.31.0; extra == "dev"
Requires-Dist: requests-toolbelt==1.0.0; extra == "dev"
Requires-Dist: rfc3986==2.0.0; extra == "dev"
Requires-Dist: rich==13.7.1; extra == "dev"
Requires-Dist: rich-argparse==1.4.0; extra == "dev"
Requires-Dist: secretstorage==3.3.3; extra == "dev"
Requires-Dist: semver==3.0.2; extra == "dev"
Requires-Dist: soupsieve==2.5; extra == "dev"
Requires-Dist: toml-sort==0.23.1; extra == "dev"
Requires-Dist: tomli==2.0.1; extra == "dev"
Requires-Dist: tomlkit==0.12.4; extra == "dev"
Requires-Dist: twine==5.0.0; extra == "dev"
Requires-Dist: types-beautifulsoup4==4.12.0.20240229; extra == "dev"
Requires-Dist: types-colorama==0.4.15.20240311; extra == "dev"
Requires-Dist: types-html5lib==1.1.11.20240228; extra == "dev"
Requires-Dist: types-pyyaml==6.0.12.20240311; extra == "dev"
Requires-Dist: typing-extensions==4.10.0; extra == "dev"
Requires-Dist: urllib3==2.2.1; extra == "dev"
Requires-Dist: virtualenv==20.25.0; extra == "dev"
Requires-Dist: wcwidth==0.2.13; extra == "dev"
Requires-Dist: wheel==0.43.0; extra == "dev"
Requires-Dist: xmltodict==0.13.0; extra == "dev"
Requires-Dist: yapf==0.40.2; extra == "dev"
Requires-Dist: yq==3.2.3; extra == "dev"
Requires-Dist: zipp==3.17.0; extra == "dev"
Provides-Extra: prod
Requires-Dist: colorama==0.4.6; extra == "prod"
Requires-Dist: defusedxml==0.7.1; extra == "prod"
Requires-Dist: jinja2==3.1.3; extra == "prod"
Requires-Dist: markdown-it-py==3.0.0; extra == "prod"
Requires-Dist: markupsafe==2.1.5; extra == "prod"
Requires-Dist: mdurl==0.1.2; extra == "prod"
Requires-Dist: pexpect==4.9.0; extra == "prod"
Requires-Dist: ptyprocess==0.7.0; extra == "prod"
Requires-Dist: pygments==2.17.2; extra == "prod"
Requires-Dist: pyyaml==6.0.1; extra == "prod"
Requires-Dist: rich==13.7.1; extra == "prod"
Requires-Dist: rich-argparse==1.4.0; extra == "prod"
Requires-Dist: types-colorama==0.4.15.20240311; extra == "prod"
Requires-Dist: types-pyyaml==6.0.12.20240311; extra == "prod"
Requires-Dist: typing-extensions==4.10.0; extra == "prod"
